ytb_up/__init__.py
ytb_up/constants.py
ytb_up/douyin.py
ytb_up/exceptions.py
ytb_up/logging.py
ytb_up/login.py
ytb_up/tiktok.py
ytb_up/utils.py
ytb_up/weixin.py
ytb_up/youtube.py
ytb_up-0.1.15.dist-info/LICENSE
ytb_up-0.1.15.dist-info/METADATA
ytb_up-0.1.15.dist-info/WHEEL
ytb_up-0.1.15.dist-info/top_level.txt
ytb_up-0.1.15.dist-info/RECORD
