Metadata-Version: 2.1
Name: ytb-up
Version: 0.1.15
Summary: auto video machine,Upload videos to YouTube using geckodriver, Firefox profiles and Selenium/playwright.
Home-page: https://github.com/wanghaisheng/youtube-auto-upload
Download-URL: https://github.com/wanghaisheng/youtube-auto-upload/tarball/v0.1.15
Author: wanghaisheng
Author-email: edwin.uestc@gmail.com
License: MIT
Classifier: Programming Language :: Python :: 3
Classifier: License :: OSI Approved :: MIT License
Classifier: Operating System :: OS Independent
Requires-Python: >=3.6
License-File: LICENSE
Requires-Dist: playwright
